gpsexchang/__init__.py
gpsexchang/cli.py
gpsexchang/converters.py
gpsexchang-0.1.0.dist-info/METADATA
gpsexchang-0.1.0.dist-info/WHEEL
gpsexchang-0.1.0.dist-info/entry_points.txt
gpsexchang-0.1.0.dist-info/RECORD
