Metadata-Version: 2.4
Name: gpsexchang
Version: 0.1.0
Summary: CLI tool to convert between GPX and FIT preserving activity metrics
Project-URL: Homepage, https://pypi.org/project/gpsexchang/
Author: OrienteeringX
License: MIT
Requires-Python: >=3.9
Requires-Dist: fit-tool>=0.9.13
Requires-Dist: fitparse>=1.2.0
Requires-Dist: gpxpy>=1.5.0
